proxmux/__init__.py
proxmux/cli.py
proxmux/discover.py
proxmux/htmlgen.py
proxmux/updates.py
proxmux/utils.py
proxmux/templates/viewer.html
proxmux-0.1.1.dist-info/licenses/LICENSE
proxmux-0.1.1.dist-info/METADATA
proxmux-0.1.1.dist-info/WHEEL
proxmux-0.1.1.dist-info/entry_points.txt
proxmux-0.1.1.dist-info/top_level.txt
proxmux-0.1.1.dist-info/RECORD
