Metadata-Version: 2.4
Name: proxmux
Version: 0.1.1
Summary: Proxmox VM and LXC discovery, inventory, and update management tool
Author-email: ingles98 <ingles98@github.com>
License: MIT
Requires-Python: >=3.8
License-File: LICENSE
Requires-Dist: PyYAML>=6.0
Requires-Dist: Jinja2>=3.1
Dynamic: license-file
